sawmil/__about__.py
sawmil/__init__.py
sawmil/bag.py
sawmil/bag_kernels.py
sawmil/kernels.py
sawmil/nsk.py
sawmil/py.typed
sawmil/quadprog.py
sawmil/sawmil.py
sawmil/smil.py
sawmil/svm.py
sawmil/utils.py
sawmil/data/__init__.py
sawmil/data/dummy.py
sawmil/data/musk.py
sawmil/solvers/__init__.py
sawmil/solvers/_daqp.py
sawmil/solvers/_gurobi.py
sawmil/solvers/_osqp.py
sawmil/solvers/objective.py
sawmil-0.2.1.dist-info/METADATA
sawmil-0.2.1.dist-info/WHEEL
sawmil-0.2.1.dist-info/licenses/LICENSE
sawmil-0.2.1.dist-info/RECORD
