Metadata-Version: 2.4
Name: sawmil
Version: 0.2.1
Summary: Open-source Python library providing a collection of Support Vector Machine (SVM) classifiers for multiple-instance learning (MIL): SVM, NSK, sMIL and sAwMIL.
Project-URL: Homepage, https://github.com/carlomarxdk/sawmil
Project-URL: Documentation, https://sawmil.readthedocs.io/en/latest/
Project-URL: Issues, https://github.com/carlomarxdk/sawmil/issues
Project-URL: Paper, https://arxiv.org/abs/2506.23921
Project-URL: DOI, https://doi.org/10.5281/zenodo.16990499
Project-URL: Citation, https://github.com/carlomarxdk/sawmil/blob/main/citation.cff
Author: Germans Savcisens, Tina Eliassi-Rad
License: MIT License
License-File: LICENSE
Keywords: MIL,bag,kernels,multiple-instance-learning,sawmil,sparse,svm
Classifier: Development Status :: 4 - Beta
Classifier: Intended Audience :: Science/Research
Classifier: License :: OSI Approved :: MIT License
Classifier: Operating System :: OS Independent
Classifier: Programming Language :: Python :: 3
Classifier: Programming Language :: Python :: 3 :: Only
Classifier: Programming Language :: Python :: 3.11
Classifier: Programming Language :: Python :: 3.12
Classifier: Programming Language :: Python :: 3.13
Classifier: Topic :: Scientific/Engineering :: Artificial Intelligence
Classifier: Topic :: Scientific/Engineering :: Information Analysis
Classifier: Topic :: Scientific/Engineering :: Mathematics
Classifier: Typing :: Typed
Requires-Python: >=3.11
Requires-Dist: numpy>=1.22
Requires-Dist: scikit-learn>=1.2
Requires-Dist: scipy>=1.16.1
Provides-Extra: daqp
Requires-Dist: daqp>=0.5; extra == 'daqp'
Provides-Extra: dev
Requires-Dist: build; extra == 'dev'
Requires-Dist: mypy; extra == 'dev'
Requires-Dist: pytest-cov; extra == 'dev'
Requires-Dist: pytest>=7; extra == 'dev'
Requires-Dist: ruff; extra == 'dev'
Requires-Dist: twine; extra == 'dev'
Provides-Extra: docs
Requires-Dist: mkdocs-bibtex; extra == 'docs'
Requires-Dist: mkdocs-gen-files>=0.5; extra == 'docs'
Requires-Dist: mkdocs-jupyter>=0.24; extra == 'docs'
Requires-Dist: mkdocs-literate-nav>=0.6; extra == 'docs'
Requires-Dist: mkdocs-material>=9.5; extra == 'docs'
Requires-Dist: mkdocs-section-index>=0.3; extra == 'docs'
Requires-Dist: mkdocs>=1.5; extra == 'docs'
Requires-Dist: mkdocstrings-python>=1.10; extra == 'docs'
Requires-Dist: mkdocstrings>=0.24; extra == 'docs'
Requires-Dist: ruff; extra == 'docs'
Provides-Extra: full
Requires-Dist: gurobipy>=12.0.3; extra == 'full'
Requires-Dist: osqp>=1.0.4; extra == 'full'
Provides-Extra: gurobi
Requires-Dist: gurobipy>=12.0.3; extra == 'gurobi'
Provides-Extra: osqp
Requires-Dist: osqp>=1.0.4; extra == 'osqp'
